bethic/EDA.py
bethic/ML.py
bethic/PCA.py
bethic/__init__.py
bethic/dashboard.py
bethic/mongo_operations.py
bethic/pca_lib.py
bethic/python_postprocess.py
bethic/python_preprocess.py
bethic/utils.py
bethicfuncs-0.0.2.dist-info/LICENSE
bethicfuncs-0.0.2.dist-info/METADATA
bethicfuncs-0.0.2.dist-info/WHEEL
bethicfuncs-0.0.2.dist-info/top_level.txt
bethicfuncs-0.0.2.dist-info/RECORD
